{
  "date": "2025-08-05",
  "score": 15.4,
  "regime": "LOW",
  "drivers": {
    "equity": {
      "label": "S&P 500 equity signal",
      "raw": "+0.00% vs 5 sessions | pressure 0.00 | relief 0.00",
      "unit": "signed 5-session move",
      "score": 0.0,
      "pressure_score": 0.0,
      "relief_score": 0.0,
      "latest_value": 6299.18994140625,
      "latest_date": "2025-08-05",
      "note": "A 5-session drawdown adds pressure. A 5-session rally adds relief and can partially offset the composite score."
    },
    "rates": {
      "label": "2Y Treasury rate pressure",
      "raw": "3.72% level, +0.00 bp vs 5 sessions",
      "unit": "60% level + 40% change",
      "score": 19.2,
      "latest_value": 3.72,
      "latest_date": "2025-08-05",
      "note": "Rates pressure reflects both the current 2Y level and any fresh 5-session rise."
    },
    "inflation": {
      "label": "Inflation expectations pressure",
      "raw": "2.41% level, +0.00 bp vs 5 sessions",
      "unit": "60% level + 40% change",
      "score": 24.6,
      "latest_value": 2.41,
      "latest_date": "2025-08-05",
      "note": "Inflation pressure reflects both the breakeven level and any fresh 5-session rise."
    },
    "volatility": {
      "label": "VIX volatility pressure",
      "raw": 17.85,
      "unit": "index level",
      "score": 17.8,
      "latest_value": 17.85,
      "latest_date": "2025-08-05",
      "note": "Higher implied volatility usually means greater market stress."
    }
  },
  "title": "2025-08-05 TACO Pressure Index Update: Low at 15.40",
  "description": "Today’s retreat-pressure snapshot for 2025-08-05: the TACO Pressure Index closed at 15.40/100, signaling a low pressure regime as inflation expectations and front-end rate pressure shaped the daily read. See the chart pack, score regime, and what drove the latest reading.",
  "hero_summary": "This custom framework combines equities, front-end rates, inflation expectations, and volatility into one daily score. On 2025-08-05, the score printed 15.40/100 in the low regime, with inflation expectations and front-end rate pressure doing most of the work."
}